[
{
    "model": "movies.youtube",
    "pk": 1,
    "fields": {
        "youtube_link": "https://www.youtube.com/embed/untosQf08e4",
        "movie": 17,
        "youtube_thumbnail": "https://i.ytimg.com/vi/untosQf08e4/default.jpg"
    }
},
{
    "model": "movies.youtube",
    "pk": 2,
    "fields": {
        "youtube_link": "https://www.youtube.com/embed/KjyqAufzel4",
        "movie": 17,
        "youtube_thumbnail": "https://i.ytimg.com/vi/KjyqAufzel4/default.jpg"
    }
},
{
    "model": "movies.youtube",
    "pk": 3,
    "fields": {
        "youtube_link": "https://www.youtube.com/embed/RpLXv0KnvxY",
        "movie": 17,
        "youtube_thumbnail": "https://i.ytimg.com/vi/RpLXv0KnvxY/default.jpg"
    }
},
{
    "model": "movies.youtube",
    "pk": 4,
    "fields": {
        "youtube_link": "https://www.youtube.com/embed/pN_7S0dPEsc",
        "movie": 17,
        "youtube_thumbnail": "https://i.ytimg.com/vi/pN_7S0dPEsc/default.jpg"
    }
},
{
    "model": "movies.youtube",
    "pk": 5,
    "fields": {
        "youtube_link": "https://www.youtube.com/embed/-YSrn9rNDDw",
        "movie": 17,
        "youtube_thumbnail": "https://i.ytimg.com/vi/-YSrn9rNDDw/default.jpg"
    }
},
{
    "model": "movies.youtube",
    "pk": 6,
    "fields": {
        "youtube_link": "https://www.youtube.com/embed/untosQf08e4",
        "movie": 17,
        "youtube_thumbnail": "https://i.ytimg.com/vi/untosQf08e4/default.jpg"
    }
},
{
    "model": "movies.youtube",
    "pk": 7,
    "fields": {
        "youtube_link": "https://www.youtube.com/embed/KjyqAufzel4",
        "movie": 17,
        "youtube_thumbnail": "https://i.ytimg.com/vi/KjyqAufzel4/default.jpg"
    }
},
{
    "model": "movies.youtube",
    "pk": 8,
    "fields": {
        "youtube_link": "https://www.youtube.com/embed/RpLXv0KnvxY",
        "movie": 17,
        "youtube_thumbnail": "https://i.ytimg.com/vi/RpLXv0KnvxY/default.jpg"
    }
},
{
    "model": "movies.youtube",
    "pk": 9,
    "fields": {
        "youtube_link": "https://www.youtube.com/embed/pN_7S0dPEsc",
        "movie": 17,
        "youtube_thumbnail": "https://i.ytimg.com/vi/pN_7S0dPEsc/default.jpg"
    }
},
{
    "model": "movies.youtube",
    "pk": 10,
    "fields": {
        "youtube_link": "https://www.youtube.com/embed/YSz8cEEuw3M",
        "movie": 17,
        "youtube_thumbnail": "https://i.ytimg.com/vi/YSz8cEEuw3M/default.jpg"
    }
},
{
    "model": "movies.youtube",
    "pk": 11,
    "fields": {
        "youtube_link": "https://www.youtube.com/embed/untosQf08e4",
        "movie": 17,
        "youtube_thumbnail": "https://i.ytimg.com/vi/untosQf08e4/default.jpg"
    }
},
{
    "model": "movies.youtube",
    "pk": 12,
    "fields": {
        "youtube_link": "https://www.youtube.com/embed/KjyqAufzel4",
        "movie": 17,
        "youtube_thumbnail": "https://i.ytimg.com/vi/KjyqAufzel4/default.jpg"
    }
},
{
    "model": "movies.youtube",
    "pk": 13,
    "fields": {
        "youtube_link": "https://www.youtube.com/embed/RpLXv0KnvxY",
        "movie": 17,
        "youtube_thumbnail": "https://i.ytimg.com/vi/RpLXv0KnvxY/default.jpg"
    }
},
{
    "model": "movies.youtube",
    "pk": 14,
    "fields": {
        "youtube_link": "https://www.youtube.com/embed/pN_7S0dPEsc",
        "movie": 17,
        "youtube_thumbnail": "https://i.ytimg.com/vi/pN_7S0dPEsc/default.jpg"
    }
},
{
    "model": "movies.youtube",
    "pk": 15,
    "fields": {
        "youtube_link": "https://www.youtube.com/embed/-YSrn9rNDDw",
        "movie": 17,
        "youtube_thumbnail": "https://i.ytimg.com/vi/-YSrn9rNDDw/default.jpg"
    }
},
{
    "model": "movies.youtube",
    "pk": 16,
    "fields": {
        "youtube_link": "https://www.youtube.com/embed/2fQSxrrwxjI",
        "movie": 101,
        "youtube_thumbnail": "https://i.ytimg.com/vi/2fQSxrrwxjI/default.jpg"
    }
},
{
    "model": "movies.youtube",
    "pk": 17,
    "fields": {
        "youtube_link": "https://www.youtube.com/embed/PQXNF6JvkgI",
        "movie": 101,
        "youtube_thumbnail": "https://i.ytimg.com/vi/PQXNF6JvkgI/default.jpg"
    }
},
{
    "model": "movies.youtube",
    "pk": 18,
    "fields": {
        "youtube_link": "https://www.youtube.com/embed/dr2yiVGfZ6E",
        "movie": 101,
        "youtube_thumbnail": "https://i.ytimg.com/vi/dr2yiVGfZ6E/default.jpg"
    }
},
{
    "model": "movies.youtube",
    "pk": 19,
    "fields": {
        "youtube_link": "https://www.youtube.com/embed/Y_lc3e4kkN0",
        "movie": 101,
        "youtube_thumbnail": "https://i.ytimg.com/vi/Y_lc3e4kkN0/default.jpg"
    }
},
{
    "model": "movies.youtube",
    "pk": 20,
    "fields": {
        "youtube_link": "https://www.youtube.com/embed/R2DwTlLG8KU",
        "movie": 101,
        "youtube_thumbnail": "https://i.ytimg.com/vi/R2DwTlLG8KU/default.jpg"
    }
},
{
    "model": "movies.youtube",
    "pk": 21,
    "fields": {
        "youtube_link": "https://www.youtube.com/embed/2fQSxrrwxjI",
        "movie": 101,
        "youtube_thumbnail": "https://i.ytimg.com/vi/2fQSxrrwxjI/default.jpg"
    }
},
{
    "model": "movies.youtube",
    "pk": 22,
    "fields": {
        "youtube_link": "https://www.youtube.com/embed/PQXNF6JvkgI",
        "movie": 101,
        "youtube_thumbnail": "https://i.ytimg.com/vi/PQXNF6JvkgI/default.jpg"
    }
},
{
    "model": "movies.youtube",
    "pk": 23,
    "fields": {
        "youtube_link": "https://www.youtube.com/embed/dr2yiVGfZ6E",
        "movie": 101,
        "youtube_thumbnail": "https://i.ytimg.com/vi/dr2yiVGfZ6E/default.jpg"
    }
},
{
    "model": "movies.youtube",
    "pk": 24,
    "fields": {
        "youtube_link": "https://www.youtube.com/embed/Y_lc3e4kkN0",
        "movie": 101,
        "youtube_thumbnail": "https://i.ytimg.com/vi/Y_lc3e4kkN0/default.jpg"
    }
},
{
    "model": "movies.youtube",
    "pk": 25,
    "fields": {
        "youtube_link": "https://www.youtube.com/embed/R2DwTlLG8KU",
        "movie": 101,
        "youtube_thumbnail": "https://i.ytimg.com/vi/R2DwTlLG8KU/default.jpg"
    }
},
{
    "model": "movies.youtube",
    "pk": 26,
    "fields": {
        "youtube_link": "https://www.youtube.com/embed/2fQSxrrwxjI",
        "movie": 101,
        "youtube_thumbnail": "https://i.ytimg.com/vi/2fQSxrrwxjI/default.jpg"
    }
},
{
    "model": "movies.youtube",
    "pk": 27,
    "fields": {
        "youtube_link": "https://www.youtube.com/embed/PQXNF6JvkgI",
        "movie": 101,
        "youtube_thumbnail": "https://i.ytimg.com/vi/PQXNF6JvkgI/default.jpg"
    }
},
{
    "model": "movies.youtube",
    "pk": 28,
    "fields": {
        "youtube_link": "https://www.youtube.com/embed/dr2yiVGfZ6E",
        "movie": 101,
        "youtube_thumbnail": "https://i.ytimg.com/vi/dr2yiVGfZ6E/default.jpg"
    }
},
{
    "model": "movies.youtube",
    "pk": 29,
    "fields": {
        "youtube_link": "https://www.youtube.com/embed/Y_lc3e4kkN0",
        "movie": 101,
        "youtube_thumbnail": "https://i.ytimg.com/vi/Y_lc3e4kkN0/default.jpg"
    }
},
{
    "model": "movies.youtube",
    "pk": 30,
    "fields": {
        "youtube_link": "https://www.youtube.com/embed/ss--bsONaMc",
        "movie": 101,
        "youtube_thumbnail": "https://i.ytimg.com/vi/ss--bsONaMc/default.jpg"
    }
},
{
    "model": "movies.youtube",
    "pk": 31,
    "fields": {
        "youtube_link": "https://www.youtube.com/embed/2fQSxrrwxjI",
        "movie": 101,
        "youtube_thumbnail": "https://i.ytimg.com/vi/2fQSxrrwxjI/default.jpg"
    }
},
{
    "model": "movies.youtube",
    "pk": 32,
    "fields": {
        "youtube_link": "https://www.youtube.com/embed/PQXNF6JvkgI",
        "movie": 101,
        "youtube_thumbnail": "https://i.ytimg.com/vi/PQXNF6JvkgI/default.jpg"
    }
},
{
    "model": "movies.youtube",
    "pk": 33,
    "fields": {
        "youtube_link": "https://www.youtube.com/embed/dr2yiVGfZ6E",
        "movie": 101,
        "youtube_thumbnail": "https://i.ytimg.com/vi/dr2yiVGfZ6E/default.jpg"
    }
},
{
    "model": "movies.youtube",
    "pk": 34,
    "fields": {
        "youtube_link": "https://www.youtube.com/embed/Y_lc3e4kkN0",
        "movie": 101,
        "youtube_thumbnail": "https://i.ytimg.com/vi/Y_lc3e4kkN0/default.jpg"
    }
},
{
    "model": "movies.youtube",
    "pk": 35,
    "fields": {
        "youtube_link": "https://www.youtube.com/embed/R2DwTlLG8KU",
        "movie": 101,
        "youtube_thumbnail": "https://i.ytimg.com/vi/R2DwTlLG8KU/default.jpg"
    }
},
{
    "model": "movies.youtube",
    "pk": 36,
    "fields": {
        "youtube_link": "https://www.youtube.com/embed/2fQSxrrwxjI",
        "movie": 101,
        "youtube_thumbnail": "https://i.ytimg.com/vi/2fQSxrrwxjI/default.jpg"
    }
},
{
    "model": "movies.youtube",
    "pk": 37,
    "fields": {
        "youtube_link": "https://www.youtube.com/embed/PQXNF6JvkgI",
        "movie": 101,
        "youtube_thumbnail": "https://i.ytimg.com/vi/PQXNF6JvkgI/default.jpg"
    }
},
{
    "model": "movies.youtube",
    "pk": 38,
    "fields": {
        "youtube_link": "https://www.youtube.com/embed/dr2yiVGfZ6E",
        "movie": 101,
        "youtube_thumbnail": "https://i.ytimg.com/vi/dr2yiVGfZ6E/default.jpg"
    }
},
{
    "model": "movies.youtube",
    "pk": 39,
    "fields": {
        "youtube_link": "https://www.youtube.com/embed/Y_lc3e4kkN0",
        "movie": 101,
        "youtube_thumbnail": "https://i.ytimg.com/vi/Y_lc3e4kkN0/default.jpg"
    }
},
{
    "model": "movies.youtube",
    "pk": 40,
    "fields": {
        "youtube_link": "https://www.youtube.com/embed/R2DwTlLG8KU",
        "movie": 101,
        "youtube_thumbnail": "https://i.ytimg.com/vi/R2DwTlLG8KU/default.jpg"
    }
},
{
    "model": "movies.youtube",
    "pk": 41,
    "fields": {
        "youtube_link": "https://www.youtube.com/embed/2fQSxrrwxjI",
        "movie": 101,
        "youtube_thumbnail": "https://i.ytimg.com/vi/2fQSxrrwxjI/default.jpg"
    }
},
{
    "model": "movies.youtube",
    "pk": 42,
    "fields": {
        "youtube_link": "https://www.youtube.com/embed/PQXNF6JvkgI",
        "movie": 101,
        "youtube_thumbnail": "https://i.ytimg.com/vi/PQXNF6JvkgI/default.jpg"
    }
},
{
    "model": "movies.youtube",
    "pk": 43,
    "fields": {
        "youtube_link": "https://www.youtube.com/embed/dr2yiVGfZ6E",
        "movie": 101,
        "youtube_thumbnail": "https://i.ytimg.com/vi/dr2yiVGfZ6E/default.jpg"
    }
},
{
    "model": "movies.youtube",
    "pk": 44,
    "fields": {
        "youtube_link": "https://www.youtube.com/embed/Y_lc3e4kkN0",
        "movie": 101,
        "youtube_thumbnail": "https://i.ytimg.com/vi/Y_lc3e4kkN0/default.jpg"
    }
},
{
    "model": "movies.youtube",
    "pk": 45,
    "fields": {
        "youtube_link": "https://www.youtube.com/embed/R2DwTlLG8KU",
        "movie": 101,
        "youtube_thumbnail": "https://i.ytimg.com/vi/R2DwTlLG8KU/default.jpg"
    }
},
{
    "model": "movies.youtube",
    "pk": 46,
    "fields": {
        "youtube_link": "https://www.youtube.com/embed/Zdzwer-xoiQ",
        "movie": 132,
        "youtube_thumbnail": "https://i.ytimg.com/vi/Zdzwer-xoiQ/default.jpg"
    }
},
{
    "model": "movies.youtube",
    "pk": 47,
    "fields": {
        "youtube_link": "https://www.youtube.com/embed/9kTBYkw3zH8",
        "movie": 132,
        "youtube_thumbnail": "https://i.ytimg.com/vi/9kTBYkw3zH8/default.jpg"
    }
},
{
    "model": "movies.youtube",
    "pk": 48,
    "fields": {
        "youtube_link": "https://www.youtube.com/embed/hDpKHJerwpQ",
        "movie": 132,
        "youtube_thumbnail": "https://i.ytimg.com/vi/hDpKHJerwpQ/default.jpg"
    }
},
{
    "model": "movies.youtube",
    "pk": 49,
    "fields": {
        "youtube_link": "https://www.youtube.com/embed/TOtPb4yXUtc",
        "movie": 132,
        "youtube_thumbnail": "https://i.ytimg.com/vi/TOtPb4yXUtc/default.jpg"
    }
},
{
    "model": "movies.youtube",
    "pk": 50,
    "fields": {
        "youtube_link": "https://www.youtube.com/embed/aur3tis5bS8",
        "movie": 132,
        "youtube_thumbnail": "https://i.ytimg.com/vi/aur3tis5bS8/default.jpg"
    }
},
{
    "model": "movies.youtube",
    "pk": 51,
    "fields": {
        "youtube_link": "https://www.youtube.com/embed/Zdzwer-xoiQ",
        "movie": 132,
        "youtube_thumbnail": "https://i.ytimg.com/vi/Zdzwer-xoiQ/default.jpg"
    }
},
{
    "model": "movies.youtube",
    "pk": 52,
    "fields": {
        "youtube_link": "https://www.youtube.com/embed/9kTBYkw3zH8",
        "movie": 132,
        "youtube_thumbnail": "https://i.ytimg.com/vi/9kTBYkw3zH8/default.jpg"
    }
},
{
    "model": "movies.youtube",
    "pk": 53,
    "fields": {
        "youtube_link": "https://www.youtube.com/embed/hDpKHJerwpQ",
        "movie": 132,
        "youtube_thumbnail": "https://i.ytimg.com/vi/hDpKHJerwpQ/default.jpg"
    }
},
{
    "model": "movies.youtube",
    "pk": 54,
    "fields": {
        "youtube_link": "https://www.youtube.com/embed/TOtPb4yXUtc",
        "movie": 132,
        "youtube_thumbnail": "https://i.ytimg.com/vi/TOtPb4yXUtc/default.jpg"
    }
},
{
    "model": "movies.youtube",
    "pk": 55,
    "fields": {
        "youtube_link": "https://www.youtube.com/embed/aur3tis5bS8",
        "movie": 132,
        "youtube_thumbnail": "https://i.ytimg.com/vi/aur3tis5bS8/default.jpg"
    }
},
{
    "model": "movies.youtube",
    "pk": 56,
    "fields": {
        "youtube_link": "https://www.youtube.com/embed/Zdzwer-xoiQ",
        "movie": 132,
        "youtube_thumbnail": "https://i.ytimg.com/vi/Zdzwer-xoiQ/default.jpg"
    }
},
{
    "model": "movies.youtube",
    "pk": 57,
    "fields": {
        "youtube_link": "https://www.youtube.com/embed/9kTBYkw3zH8",
        "movie": 132,
        "youtube_thumbnail": "https://i.ytimg.com/vi/9kTBYkw3zH8/default.jpg"
    }
},
{
    "model": "movies.youtube",
    "pk": 58,
    "fields": {
        "youtube_link": "https://www.youtube.com/embed/TOtPb4yXUtc",
        "movie": 132,
        "youtube_thumbnail": "https://i.ytimg.com/vi/TOtPb4yXUtc/default.jpg"
    }
},
{
    "model": "movies.youtube",
    "pk": 59,
    "fields": {
        "youtube_link": "https://www.youtube.com/embed/hDpKHJerwpQ",
        "movie": 132,
        "youtube_thumbnail": "https://i.ytimg.com/vi/hDpKHJerwpQ/default.jpg"
    }
},
{
    "model": "movies.youtube",
    "pk": 60,
    "fields": {
        "youtube_link": "https://www.youtube.com/embed/aur3tis5bS8",
        "movie": 132,
        "youtube_thumbnail": "https://i.ytimg.com/vi/aur3tis5bS8/default.jpg"
    }
},
{
    "model": "movies.youtube",
    "pk": 61,
    "fields": {
        "youtube_link": "https://www.youtube.com/embed/Zdzwer-xoiQ",
        "movie": 132,
        "youtube_thumbnail": "https://i.ytimg.com/vi/Zdzwer-xoiQ/default.jpg"
    }
},
{
    "model": "movies.youtube",
    "pk": 62,
    "fields": {
        "youtube_link": "https://www.youtube.com/embed/9kTBYkw3zH8",
        "movie": 132,
        "youtube_thumbnail": "https://i.ytimg.com/vi/9kTBYkw3zH8/default.jpg"
    }
},
{
    "model": "movies.youtube",
    "pk": 63,
    "fields": {
        "youtube_link": "https://www.youtube.com/embed/hDpKHJerwpQ",
        "movie": 132,
        "youtube_thumbnail": "https://i.ytimg.com/vi/hDpKHJerwpQ/default.jpg"
    }
},
{
    "model": "movies.youtube",
    "pk": 64,
    "fields": {
        "youtube_link": "https://www.youtube.com/embed/TOtPb4yXUtc",
        "movie": 132,
        "youtube_thumbnail": "https://i.ytimg.com/vi/TOtPb4yXUtc/default.jpg"
    }
},
{
    "model": "movies.youtube",
    "pk": 65,
    "fields": {
        "youtube_link": "https://www.youtube.com/embed/aur3tis5bS8",
        "movie": 132,
        "youtube_thumbnail": "https://i.ytimg.com/vi/aur3tis5bS8/default.jpg"
    }
},
{
    "model": "movies.youtube",
    "pk": 66,
    "fields": {
        "youtube_link": "https://www.youtube.com/embed/Zdzwer-xoiQ",
        "movie": 132,
        "youtube_thumbnail": "https://i.ytimg.com/vi/Zdzwer-xoiQ/default.jpg"
    }
},
{
    "model": "movies.youtube",
    "pk": 67,
    "fields": {
        "youtube_link": "https://www.youtube.com/embed/9kTBYkw3zH8",
        "movie": 132,
        "youtube_thumbnail": "https://i.ytimg.com/vi/9kTBYkw3zH8/default.jpg"
    }
},
{
    "model": "movies.youtube",
    "pk": 68,
    "fields": {
        "youtube_link": "https://www.youtube.com/embed/hDpKHJerwpQ",
        "movie": 132,
        "youtube_thumbnail": "https://i.ytimg.com/vi/hDpKHJerwpQ/default.jpg"
    }
},
{
    "model": "movies.youtube",
    "pk": 69,
    "fields": {
        "youtube_link": "https://www.youtube.com/embed/TOtPb4yXUtc",
        "movie": 132,
        "youtube_thumbnail": "https://i.ytimg.com/vi/TOtPb4yXUtc/default.jpg"
    }
},
{
    "model": "movies.youtube",
    "pk": 70,
    "fields": {
        "youtube_link": "https://www.youtube.com/embed/aur3tis5bS8",
        "movie": 132,
        "youtube_thumbnail": "https://i.ytimg.com/vi/aur3tis5bS8/default.jpg"
    }
},
{
    "model": "movies.youtube",
    "pk": 71,
    "fields": {
        "youtube_link": "https://www.youtube.com/embed/Zdzwer-xoiQ",
        "movie": 132,
        "youtube_thumbnail": "https://i.ytimg.com/vi/Zdzwer-xoiQ/default.jpg"
    }
},
{
    "model": "movies.youtube",
    "pk": 72,
    "fields": {
        "youtube_link": "https://www.youtube.com/embed/9kTBYkw3zH8",
        "movie": 132,
        "youtube_thumbnail": "https://i.ytimg.com/vi/9kTBYkw3zH8/default.jpg"
    }
},
{
    "model": "movies.youtube",
    "pk": 73,
    "fields": {
        "youtube_link": "https://www.youtube.com/embed/hDpKHJerwpQ",
        "movie": 132,
        "youtube_thumbnail": "https://i.ytimg.com/vi/hDpKHJerwpQ/default.jpg"
    }
},
{
    "model": "movies.youtube",
    "pk": 74,
    "fields": {
        "youtube_link": "https://www.youtube.com/embed/TOtPb4yXUtc",
        "movie": 132,
        "youtube_thumbnail": "https://i.ytimg.com/vi/TOtPb4yXUtc/default.jpg"
    }
},
{
    "model": "movies.youtube",
    "pk": 75,
    "fields": {
        "youtube_link": "https://www.youtube.com/embed/aur3tis5bS8",
        "movie": 132,
        "youtube_thumbnail": "https://i.ytimg.com/vi/aur3tis5bS8/default.jpg"
    }
},
{
    "model": "movies.youtube",
    "pk": 76,
    "fields": {
        "youtube_link": "https://www.youtube.com/embed/Zdzwer-xoiQ",
        "movie": 132,
        "youtube_thumbnail": "https://i.ytimg.com/vi/Zdzwer-xoiQ/default.jpg"
    }
},
{
    "model": "movies.youtube",
    "pk": 77,
    "fields": {
        "youtube_link": "https://www.youtube.com/embed/9kTBYkw3zH8",
        "movie": 132,
        "youtube_thumbnail": "https://i.ytimg.com/vi/9kTBYkw3zH8/default.jpg"
    }
},
{
    "model": "movies.youtube",
    "pk": 78,
    "fields": {
        "youtube_link": "https://www.youtube.com/embed/hDpKHJerwpQ",
        "movie": 132,
        "youtube_thumbnail": "https://i.ytimg.com/vi/hDpKHJerwpQ/default.jpg"
    }
},
{
    "model": "movies.youtube",
    "pk": 79,
    "fields": {
        "youtube_link": "https://www.youtube.com/embed/TOtPb4yXUtc",
        "movie": 132,
        "youtube_thumbnail": "https://i.ytimg.com/vi/TOtPb4yXUtc/default.jpg"
    }
},
{
    "model": "movies.youtube",
    "pk": 80,
    "fields": {
        "youtube_link": "https://www.youtube.com/embed/aur3tis5bS8",
        "movie": 132,
        "youtube_thumbnail": "https://i.ytimg.com/vi/aur3tis5bS8/default.jpg"
    }
},
{
    "model": "movies.youtube",
    "pk": 81,
    "fields": {
        "youtube_link": "https://www.youtube.com/embed/Zdzwer-xoiQ",
        "movie": 132,
        "youtube_thumbnail": "https://i.ytimg.com/vi/Zdzwer-xoiQ/default.jpg"
    }
},
{
    "model": "movies.youtube",
    "pk": 82,
    "fields": {
        "youtube_link": "https://www.youtube.com/embed/9kTBYkw3zH8",
        "movie": 132,
        "youtube_thumbnail": "https://i.ytimg.com/vi/9kTBYkw3zH8/default.jpg"
    }
},
{
    "model": "movies.youtube",
    "pk": 83,
    "fields": {
        "youtube_link": "https://www.youtube.com/embed/hDpKHJerwpQ",
        "movie": 132,
        "youtube_thumbnail": "https://i.ytimg.com/vi/hDpKHJerwpQ/default.jpg"
    }
},
{
    "model": "movies.youtube",
    "pk": 84,
    "fields": {
        "youtube_link": "https://www.youtube.com/embed/TOtPb4yXUtc",
        "movie": 132,
        "youtube_thumbnail": "https://i.ytimg.com/vi/TOtPb4yXUtc/default.jpg"
    }
},
{
    "model": "movies.youtube",
    "pk": 85,
    "fields": {
        "youtube_link": "https://www.youtube.com/embed/aur3tis5bS8",
        "movie": 132,
        "youtube_thumbnail": "https://i.ytimg.com/vi/aur3tis5bS8/default.jpg"
    }
},
{
    "model": "movies.youtube",
    "pk": 86,
    "fields": {
        "youtube_link": "https://www.youtube.com/embed/Zdzwer-xoiQ",
        "movie": 132,
        "youtube_thumbnail": "https://i.ytimg.com/vi/Zdzwer-xoiQ/default.jpg"
    }
},
{
    "model": "movies.youtube",
    "pk": 87,
    "fields": {
        "youtube_link": "https://www.youtube.com/embed/9kTBYkw3zH8",
        "movie": 132,
        "youtube_thumbnail": "https://i.ytimg.com/vi/9kTBYkw3zH8/default.jpg"
    }
},
{
    "model": "movies.youtube",
    "pk": 88,
    "fields": {
        "youtube_link": "https://www.youtube.com/embed/hDpKHJerwpQ",
        "movie": 132,
        "youtube_thumbnail": "https://i.ytimg.com/vi/hDpKHJerwpQ/default.jpg"
    }
},
{
    "model": "movies.youtube",
    "pk": 89,
    "fields": {
        "youtube_link": "https://www.youtube.com/embed/TOtPb4yXUtc",
        "movie": 132,
        "youtube_thumbnail": "https://i.ytimg.com/vi/TOtPb4yXUtc/default.jpg"
    }
},
{
    "model": "movies.youtube",
    "pk": 90,
    "fields": {
        "youtube_link": "https://www.youtube.com/embed/aur3tis5bS8",
        "movie": 132,
        "youtube_thumbnail": "https://i.ytimg.com/vi/aur3tis5bS8/default.jpg"
    }
},
{
    "model": "movies.youtube",
    "pk": 91,
    "fields": {
        "youtube_link": "https://www.youtube.com/embed/2fQSxrrwxjI",
        "movie": 101,
        "youtube_thumbnail": "https://i.ytimg.com/vi/2fQSxrrwxjI/default.jpg"
    }
},
{
    "model": "movies.youtube",
    "pk": 92,
    "fields": {
        "youtube_link": "https://www.youtube.com/embed/PQXNF6JvkgI",
        "movie": 101,
        "youtube_thumbnail": "https://i.ytimg.com/vi/PQXNF6JvkgI/default.jpg"
    }
},
{
    "model": "movies.youtube",
    "pk": 93,
    "fields": {
        "youtube_link": "https://www.youtube.com/embed/dr2yiVGfZ6E",
        "movie": 101,
        "youtube_thumbnail": "https://i.ytimg.com/vi/dr2yiVGfZ6E/default.jpg"
    }
},
{
    "model": "movies.youtube",
    "pk": 94,
    "fields": {
        "youtube_link": "https://www.youtube.com/embed/Y_lc3e4kkN0",
        "movie": 101,
        "youtube_thumbnail": "https://i.ytimg.com/vi/Y_lc3e4kkN0/default.jpg"
    }
},
{
    "model": "movies.youtube",
    "pk": 95,
    "fields": {
        "youtube_link": "https://www.youtube.com/embed/R2DwTlLG8KU",
        "movie": 101,
        "youtube_thumbnail": "https://i.ytimg.com/vi/R2DwTlLG8KU/default.jpg"
    }
},
{
    "model": "movies.youtube",
    "pk": 96,
    "fields": {
        "youtube_link": "https://www.youtube.com/embed/CBddtwQj4Jw",
        "movie": 145,
        "youtube_thumbnail": "https://i.ytimg.com/vi/CBddtwQj4Jw/default.jpg"
    }
},
{
    "model": "movies.youtube",
    "pk": 97,
    "fields": {
        "youtube_link": "https://www.youtube.com/embed/vKTZEacUysg",
        "movie": 145,
        "youtube_thumbnail": "https://i.ytimg.com/vi/vKTZEacUysg/default.jpg"
    }
},
{
    "model": "movies.youtube",
    "pk": 98,
    "fields": {
        "youtube_link": "https://www.youtube.com/embed/-AfsTWjEHUU",
        "movie": 145,
        "youtube_thumbnail": "https://i.ytimg.com/vi/-AfsTWjEHUU/default.jpg"
    }
},
{
    "model": "movies.youtube",
    "pk": 99,
    "fields": {
        "youtube_link": "https://www.youtube.com/embed/oHry7947TQw",
        "movie": 145,
        "youtube_thumbnail": "https://i.ytimg.com/vi/oHry7947TQw/default.jpg"
    }
},
{
    "model": "movies.youtube",
    "pk": 100,
    "fields": {
        "youtube_link": "https://www.youtube.com/embed/Zi1ZXv1nDC4",
        "movie": 145,
        "youtube_thumbnail": "https://i.ytimg.com/vi/Zi1ZXv1nDC4/default.jpg"
    }
},
{
    "model": "movies.youtube",
    "pk": 101,
    "fields": {
        "youtube_link": "https://www.youtube.com/embed/DYIFDxV-vVg",
        "movie": 162,
        "youtube_thumbnail": "https://i.ytimg.com/vi/DYIFDxV-vVg/default.jpg"
    }
},
{
    "model": "movies.youtube",
    "pk": 102,
    "fields": {
        "youtube_link": "https://www.youtube.com/embed/JPuVGwHgXD0",
        "movie": 162,
        "youtube_thumbnail": "https://i.ytimg.com/vi/JPuVGwHgXD0/default.jpg"
    }
},
{
    "model": "movies.youtube",
    "pk": 103,
    "fields": {
        "youtube_link": "https://www.youtube.com/embed/XGn7E_qhTBE",
        "movie": 162,
        "youtube_thumbnail": "https://i.ytimg.com/vi/XGn7E_qhTBE/default.jpg"
    }
},
{
    "model": "movies.youtube",
    "pk": 104,
    "fields": {
        "youtube_link": "https://www.youtube.com/embed/vTvbo2y1W6E",
        "movie": 162,
        "youtube_thumbnail": "https://i.ytimg.com/vi/vTvbo2y1W6E/default.jpg"
    }
},
{
    "model": "movies.youtube",
    "pk": 105,
    "fields": {
        "youtube_link": "https://www.youtube.com/embed/R3MqQKuWwSQ",
        "movie": 162,
        "youtube_thumbnail": "https://i.ytimg.com/vi/R3MqQKuWwSQ/default.jpg"
    }
},
{
    "model": "movies.youtube",
    "pk": 106,
    "fields": {
        "youtube_link": "https://www.youtube.com/embed/DYIFDxV-vVg",
        "movie": 162,
        "youtube_thumbnail": "https://i.ytimg.com/vi/DYIFDxV-vVg/default.jpg"
    }
},
{
    "model": "movies.youtube",
    "pk": 107,
    "fields": {
        "youtube_link": "https://www.youtube.com/embed/vTvbo2y1W6E",
        "movie": 162,
        "youtube_thumbnail": "https://i.ytimg.com/vi/vTvbo2y1W6E/default.jpg"
    }
},
{
    "model": "movies.youtube",
    "pk": 108,
    "fields": {
        "youtube_link": "https://www.youtube.com/embed/XGn7E_qhTBE",
        "movie": 162,
        "youtube_thumbnail": "https://i.ytimg.com/vi/XGn7E_qhTBE/default.jpg"
    }
},
{
    "model": "movies.youtube",
    "pk": 109,
    "fields": {
        "youtube_link": "https://www.youtube.com/embed/JPuVGwHgXD0",
        "movie": 162,
        "youtube_thumbnail": "https://i.ytimg.com/vi/JPuVGwHgXD0/default.jpg"
    }
},
{
    "model": "movies.youtube",
    "pk": 110,
    "fields": {
        "youtube_link": "https://www.youtube.com/embed/R3MqQKuWwSQ",
        "movie": 162,
        "youtube_thumbnail": "https://i.ytimg.com/vi/R3MqQKuWwSQ/default.jpg"
    }
},
{
    "model": "movies.youtube",
    "pk": 111,
    "fields": {
        "youtube_link": "https://www.youtube.com/embed/CyLUd8bQwlc",
        "movie": 1,
        "youtube_thumbnail": "https://i.ytimg.com/vi/CyLUd8bQwlc/default.jpg"
    }
},
{
    "model": "movies.youtube",
    "pk": 112,
    "fields": {
        "youtube_link": "https://www.youtube.com/embed/N1oFprb-shc",
        "movie": 1,
        "youtube_thumbnail": "https://i.ytimg.com/vi/N1oFprb-shc/default.jpg"
    }
},
{
    "model": "movies.youtube",
    "pk": 113,
    "fields": {
        "youtube_link": "https://www.youtube.com/embed/k8cqCKAS1Y0",
        "movie": 1,
        "youtube_thumbnail": "https://i.ytimg.com/vi/k8cqCKAS1Y0/default.jpg"
    }
},
{
    "model": "movies.youtube",
    "pk": 114,
    "fields": {
        "youtube_link": "https://www.youtube.com/embed/ln3nDsVe5eg",
        "movie": 1,
        "youtube_thumbnail": "https://i.ytimg.com/vi/ln3nDsVe5eg/default.jpg"
    }
},
{
    "model": "movies.youtube",
    "pk": 115,
    "fields": {
        "youtube_link": "https://www.youtube.com/embed/OFowbeiGEC4",
        "movie": 1,
        "youtube_thumbnail": "https://i.ytimg.com/vi/OFowbeiGEC4/default.jpg"
    }
}
]
